eyeball_pp/__init__.py
eyeball_pp/classes.py
eyeball_pp/comparators.py
eyeball_pp/compare_checkpoints.py
eyeball_pp/eval.py
eyeball_pp/graders.py
eyeball_pp/llm_utils.py
eyeball_pp/recorders.py
eyeball_pp/system_state.py
eyeball_pp/utils.py
eyeball_pp-0.0.15.dist-info/LICENSE
eyeball_pp-0.0.15.dist-info/METADATA
eyeball_pp-0.0.15.dist-info/WHEEL
eyeball_pp-0.0.15.dist-info/entry_points.txt
eyeball_pp-0.0.15.dist-info/top_level.txt
eyeball_pp-0.0.15.dist-info/RECORD
