Metadata-Version: 2.1
Name: eyeball-pp
Version: 0.0.15
Summary: A python package for evaluating tasks which use llms
Home-page: https://github.com/revantk/eyeball-plus-plus
Author: Revant
Author-email: revant.kapoor@gmail.com
Classifier: Programming Language :: Python :: 3
Classifier: Operating System :: OS Independent
License-File: LICENSE
